pyrustor-0.1.19.dist-info/METADATA
pyrustor-0.1.19.dist-info/WHEEL
pyrustor-0.1.19.dist-info/licenses/LICENSE
pyrustor/__init__.py
pyrustor/__init__.py.bak
pyrustor/_pyrustor.cpython-312-x86_64-linux-gnu.so
pyrustor/_pyrustor.pyi
pyrustor/py.typed
pyrustor-0.1.19.dist-info/RECORD
