Metadata-Version: 2.4
Name: pyrustor
Version: 0.1.19
Classifier: Development Status :: 4 - Beta
Classifier: Intended Audience :: Developers
Classifier: License :: OSI Approved :: MIT License
Classifier: Programming Language :: Rust
Classifier: Programming Language :: Python :: Implementation :: CPython
Classifier: Programming Language :: Python :: Implementation :: PyPy
Classifier: Programming Language :: Python :: 3
Classifier: Programming Language :: Python :: 3.8
Classifier: Programming Language :: Python :: 3.9
Classifier: Programming Language :: Python :: 3.10
Classifier: Programming Language :: Python :: 3.11
Classifier: Programming Language :: Python :: 3.12
Classifier: Programming Language :: Python :: 3.13
Classifier: Topic :: Software Development :: Libraries :: Python Modules
Classifier: Topic :: Software Development :: Code Generators
Classifier: Topic :: Text Processing :: Linguistic
License-File: LICENSE
Summary: A high-performance Python code parsing and refactoring tool written in Rust
Keywords: python,parser,refactoring,ast,code-analysis,rust
Home-Page: https://github.com/loonghao/PyRustor
Author-email: Hal <hal.long@outlook.com>
Requires-Python: >=3.8
Project-URL: Homepage, https://github.com/loonghao/PyRustor
Project-URL: Repository, https://github.com/loonghao/PyRustor
Project-URL: Documentation, https://github.com/loonghao/PyRustor
Project-URL: Bug Tracker, https://github.com/loonghao/PyRustor/issues
